entropy_based_binning/__init__.py
entropy_based_binning/_main.py
entropy_based_binning-0.0.1.dist-info/DESCRIPTION.rst
entropy_based_binning-0.0.1.dist-info/METADATA
entropy_based_binning-0.0.1.dist-info/RECORD
entropy_based_binning-0.0.1.dist-info/WHEEL
entropy_based_binning-0.0.1.dist-info/metadata.json
entropy_based_binning-0.0.1.dist-info/top_level.txt
