Metadata-Version: 1.1
Name: entropy-based-binning
Version: 0.0.1
Summary: Entropy based binning of discrete variables.
Home-page: https://github.com/paulbrodersen/entropy_based_binning
Author: Paul Brodersen
Author-email: paulbrodersen+ebb@gmail.com
License: UNKNOWN
Download-URL: https://github.com/paulbrodersen/entropy_based_binning/archive/0.0.1.tar.gz
Keywords: entropy,binning,partition problem
Platform: Platform Independent
Classifier: Development Status :: 4 - Beta
Classifier: Intended Audience :: Science/Research
Classifier: License :: OSI Approved :: MIT License
Classifier: Operating System :: OS Independent
Classifier: Programming Language :: Python :: 2
Classifier: Programming Language :: Python :: 3
Classifier: Topic :: Scientific/Engineering :: Mathematics
